{
  "packages": [
    {
      "name": "AliyfiaBoard_IOAI",
      "maintainer": "Your Name",
      "websiteURL": "https://github.com/aliyfia/AliyfiaBoard_IOAI",
      "email": "aliyfiaalfi@gmail.com",
      "help": {
        "online": "https://github.com/aliyfia/AliyfiaBoard_IOAI"
      },
      "platforms": [
        {
          "name": "AliyfiaBoard IOAI",
          "architecture": "esp32",
          "version": "1.0.0",
          "category": "Contributed",
          "url": "https://github.com/aliyfia/AliyfiaBoard_IOAI/releases/download/1.0.0/AliyfiaBoard_IOAI.zip",
          "archiveFileName": "AliyfiaBoard_IOAI.zip",
          "checksum": "SHA-256:c1bb2eba0527ebf7ef6900c87e03bd78e43f847148ba09806af1d034247518f2",
          "size": "48812492",
          "boards": [
            { "name": "AliyfiaBoard_IOAI" }
          ],
          "toolsDependencies": [
            {
              "packager": "AliyfiaBoard_IOAI",
              "name": "xtensa-esp32-elf-gcc",
              "version": "1.22.0-80-g6c4433a-5.2.0"
            }
          ]
        }
      ]
    }
  ]
}
